.bumpversion.cfg
.cookiecutterrc
.coveragerc
.editorconfig
.pre-commit-config.yaml
.readthedocs.yml
AUTHORS.rst
CHANGELOG.rst
CONTRIBUTING.rst
LICENSE
MANIFEST.in
README.rst
pytest.ini
setup.cfg
setup.py
tox.ini
.github/workflows/github-actions.yml
ci/bootstrap.py
ci/requirements.txt
ci/templates/.github/workflows/github-actions.yml
docs/authors.rst
docs/changelog.rst
docs/conf.py
docs/contributing.rst
docs/index.rst
docs/installation.rst
docs/readme.rst
docs/requirements.txt
docs/spelling_wordlist.txt
docs/usage.rst
docs/reference/ericdemo.rst
docs/reference/index.rst
src/.DS_Store
src/ericdemo/__init__.py
src/ericdemo/__main__.py
src/ericdemo/cli.py
src/ericdemo/ericdemo.py
src/ericdemo.egg-info/PKG-INFO
src/ericdemo.egg-info/SOURCES.txt
src/ericdemo.egg-info/dependency_links.txt
src/ericdemo.egg-info/entry_points.txt
src/ericdemo.egg-info/not-zip-safe
src/ericdemo.egg-info/top_level.txt
tests/test_ericdemo.py