Metadata-Version: 1.2
Name: ericdemo
Version: 0.0.1
Summary: Demo of creating and uploading a package
Home-page: https://github.com/ericchagnon15/ericdemo
Author: Eric Chagnon
Author-email: eric.chagnon15@gmail.com
License: MIT
Project-URL: Issue Tracker, https://github.com/ericchagnon15/ericdemo/issues
Project-URL: Documentation, https://ericdemo.readthedocs.io/
Project-URL: Changelog, https://ericdemo.readthedocs.io/en/latest/changelog.html
Platform: UNKNOWN
Classifier: Development Status :: 5 - Production/Stable
Classifier: Intended Audience :: Developers
Classifier: License :: OSI Approved :: MIT License
Classifier: Operating System :: Unix
Classifier: Operating System :: POSIX
Classifier: Operating System :: Microsoft :: Windows
Classifier: Programming Language :: Python
Classifier: Programming Language :: Python :: 3
Classifier: Programming Language :: Python :: 3 :: Only
Classifier: Programming Language :: Python :: 3.6
Classifier: Programming Language :: Python :: 3.7
Classifier: Programming Language :: Python :: 3.8
Classifier: Programming Language :: Python :: 3.9
Classifier: Programming Language :: Python :: 3.10
Classifier: Programming Language :: Python :: Implementation :: CPython
Classifier: Programming Language :: Python :: Implementation :: PyPy
Classifier: Topic :: Utilities
Requires-Python: >=3.6
